flask_admin_csv_model/__init__.py
flask_admin_csv_model/contrib/__init__.py
flask_admin_csv_model/contrib/csv/__init__.py
flask_admin_csv_model/contrib/csv/model.py
flask_admin_csv_model/contrib/csv/view.py
flask_admin_csv_model-0.0.1.dist-info/LICENSE.md
flask_admin_csv_model-0.0.1.dist-info/METADATA
flask_admin_csv_model-0.0.1.dist-info/WHEEL
flask_admin_csv_model-0.0.1.dist-info/top_level.txt
flask_admin_csv_model-0.0.1.dist-info/RECORD
