Metadata-Version: 2.1
Name: flask-admin-csv-model
Version: 0.0.1
Summary: A CSV-file model backend for Flask-Admin
Home-page: https://github.com/fholmer/flask-admin-csv-model
Author: Frode Holmer
Author-email: fholmer+flask@gmail.com
License: BSD-3-Clause
Project-URL: Source Code, https://github.com/fholmer/flask-admin-csv-model
Keywords: flask-admin,csv
Classifier: Framework :: Flask
Classifier: Development Status :: 4 - Beta
Classifier: Environment :: Web Environment
Classifier: Intended Audience :: Developers
Classifier: License :: OSI Approved :: BSD License
Classifier: Operating System :: OS Independent
Classifier: Programming Language :: Python :: 3
License-File: LICENSE.md
Requires-Dist: Flask
Requires-Dist: Flask-Admin
